jupyterlab_server/__init__.py
jupyterlab_server/__main__.py
jupyterlab_server/_version.py
jupyterlab_server/app.py
jupyterlab_server/config.py
jupyterlab_server/handlers.py
jupyterlab_server/licenses_app.py
jupyterlab_server/licenses_handler.py
jupyterlab_server/listings_handler.py
jupyterlab_server/process.py
jupyterlab_server/process_app.py
jupyterlab_server/pytest_plugin.py
jupyterlab_server/rest-api.yml
jupyterlab_server/server.py
jupyterlab_server/settings_handler.py
jupyterlab_server/settings_utils.py
jupyterlab_server/spec.py
jupyterlab_server/test_utils.py
jupyterlab_server/themes_handler.py
jupyterlab_server/translation_utils.py
jupyterlab_server/translations_handler.py
jupyterlab_server/workspaces_app.py
jupyterlab_server/workspaces_handler.py
jupyterlab_server/templates/403.html
jupyterlab_server/templates/error.html
jupyterlab_server/templates/index.html
jupyterlab_server/test_data/app-settings/overrides.json
jupyterlab_server/test_data/schemas/@jupyterlab/apputils-extension/themes.json
jupyterlab_server/test_data/schemas/@jupyterlab/codemirror-extension/commands.json
jupyterlab_server/test_data/schemas/@jupyterlab/shortcuts-extension/package.json.orig
jupyterlab_server/test_data/schemas/@jupyterlab/shortcuts-extension/plugin.json
jupyterlab_server/test_data/schemas/@jupyterlab/translation-extension/plugin.json
jupyterlab_server/test_data/schemas/@jupyterlab/unicode-extension/plugin.json
jupyterlab_server/test_data/workspaces/foo-2c26.jupyterlab-workspace
jupyterlab_server/test_data/workspaces/foo-92dd.jupyterlab-workspace
jupyterlab_server-2.13.0.dist-info/LICENSE
jupyterlab_server-2.13.0.dist-info/METADATA
jupyterlab_server-2.13.0.dist-info/WHEEL
jupyterlab_server-2.13.0.dist-info/top_level.txt
jupyterlab_server-2.13.0.dist-info/RECORD
