Metadata-Version: 2.1
Name: jupyterlab_server
Version: 2.13.0
Summary: A set of server components for JupyterLab and JupyterLab like applications .
Home-page: https://jupyterlab-server.readthedocs.io
Author: Jupyter Development Team
Author-email: jupyter@googlegroups.com
License: UNKNOWN
Project-URL: Documentation, https://jupyterlab-server.readthedocs.io
Project-URL: Funding, https://numfocus.org/donate-to-jupyter
Project-URL: Source, https://github.com/jupyterlab/jupyterlab_server
Project-URL: Tracker, https://github.com/jupyterlab/jupyterlab_server/issues
Keywords: jupyter,jupyterlab
Platform: Linux
Platform: Mac OS X
Platform: Windows
Classifier: Framework :: Jupyter
Classifier: Framework :: Jupyter :: JupyterLab
Classifier: Intended Audience :: Developers
Classifier: Intended Audience :: Science/Research
Classifier: Intended Audience :: System Administrators
Classifier: License :: OSI Approved :: BSD License
Classifier: Programming Language :: Python
Classifier: Programming Language :: Python :: 3 :: Only
Classifier: Programming Language :: Python :: 3.7
Classifier: Programming Language :: Python :: 3.8
Classifier: Programming Language :: Python :: 3.9
Classifier: Programming Language :: Python :: 3.10
Requires-Python: >=3.7
Provides-Extra: openapi
Provides-Extra: test
License-File: LICENSE
